quipy/__init__.py
quipy/ops.py
quipy/dense/__init__.py
quipy/dense/circuit.py
quipy/dense/state.py
quipy/sparse/__init__.py
quipy/sparse/circuit.py
quipy/sparse/state.py
quipy-0.1.1.dist-info/licenses/LICENSE
quipy-0.1.1.dist-info/METADATA
quipy-0.1.1.dist-info/WHEEL
quipy-0.1.1.dist-info/top_level.txt
quipy-0.1.1.dist-info/RECORD
