Metadata-Version: 2.4
Name: quipy
Version: 0.1.1
Summary: Quantum circuit simulator with sparse and dense implementations
Author-email: Vladimir Dabić <vddabic@gmail.com>
Project-URL: Homepage, https://github.com/vladimirdabic/quipy
Project-URL: Repository, https://github.com/vladimirdabic/quipy
Keywords: quantum,quantum computing,simulation,quantum circuits,quantum information
Classifier: Programming Language :: Python :: 3
Classifier: License :: OSI Approved :: MIT License
Classifier: Operating System :: OS Independent
Requires-Python: >=3.11
License-File: LICENSE
Requires-Dist: numpy
Dynamic: license-file
